task_scheduling/__init__.py
task_scheduling/__main__.py
task_scheduling/task_creation.py
task_scheduling/variable.py
task_scheduling/client/__init__.py
task_scheduling/client/rpc_client.py
task_scheduling/client/submit.py
task_scheduling/client/utils/__init__.py
task_scheduling/client/utils/core.py
task_scheduling/common/__init__.py
task_scheduling/common/config.json
task_scheduling/common/config.py
task_scheduling/common/logger.py
task_scheduling/construct/__init__.py
task_scheduling/construct/followup_creation.py
task_scheduling/construct/quick_creation.py
task_scheduling/construct/retry_task_creation.py
task_scheduling/construct/utils/__init__.py
task_scheduling/construct/utils/branch_creation.py
task_scheduling/control/__init__.py
task_scheduling/control/process_control.py
task_scheduling/control/thread_control.py
task_scheduling/control_server/__init__.py
task_scheduling/control_server/control.py
task_scheduling/control_server/utils/__init__.py
task_scheduling/control_server/utils/core.py
task_scheduling/handling/__init__.py
task_scheduling/handling/pause_handling.py
task_scheduling/handling/terminate_handling.py
task_scheduling/handling/timeout_handling.py
task_scheduling/handling/utils/__init__.py
task_scheduling/handling/utils/timout_base.py
task_scheduling/main_server/__init__.py
task_scheduling/main_server/__main__.py
task_scheduling/main_server/server.py
task_scheduling/main_server/utils/__init__.py
task_scheduling/main_server/utils/core.py
task_scheduling/manager/__init__.py
task_scheduling/manager/details_manager.py
task_scheduling/manager/info_manager.py
task_scheduling/manager/scheduler_manager.py
task_scheduling/proxy_server/__init__.py
task_scheduling/proxy_server/__main__.py
task_scheduling/proxy_server/proxy.py
task_scheduling/proxy_server/utils/__init__.py
task_scheduling/proxy_server/utils/core.py
task_scheduling/result_server/__init__.py
task_scheduling/result_server/get_result.py
task_scheduling/result_server/get_service.py
task_scheduling-6.1.1.dist-info/licenses/LICENSE
task_scheduling-6.1.1.dist-info/METADATA
task_scheduling-6.1.1.dist-info/WHEEL
task_scheduling-6.1.1.dist-info/top_level.txt
task_scheduling-6.1.1.dist-info/RECORD
