Metadata-Version: 2.4
Name: task_scheduling
Version: 6.1.1
Summary: It is mainly used for task scheduling
Author-email: fallingmeteorite <2327667836@qq.com>
License-Expression: MIT
Project-URL: Homepage, https://github.com/fallingmeteorite/task_scheduling
Project-URL: Bug Tracker, https://github.com/fallingmeteorite/task_scheduling/issues
Classifier: Programming Language :: Python :: 3.7
Classifier: Programming Language :: Python :: 3.8
Classifier: Programming Language :: Python :: 3.9
Classifier: Programming Language :: Python :: 3.10
Classifier: Programming Language :: Python :: 3.11
Classifier: Programming Language :: Python :: 3.12
Classifier: Programming Language :: Python :: 3.13
Classifier: Programming Language :: Python :: 3.14
Classifier: Operating System :: OS Independent
Requires-Python: >=3.7
License-File: LICENSE
Requires-Dist: loguru
Requires-Dist: dill
Dynamic: license-file
